adjusted_r2_score/__init__.py
adjusted_r2_score/core.py
adjusted_r2_score-0.0.1.dist-info/METADATA
adjusted_r2_score-0.0.1.dist-info/WHEEL
adjusted_r2_score-0.0.1.dist-info/licenses/LICENSE
adjusted_r2_score-0.0.1.dist-info/RECORD
